{"name":"Multi-column-select","tagline":"Jquery/CSS Multi Column Select Box Replacement.","body":"<h1>Multi-Column-Select</h1>\r\n\r\n\r\n\r\n![alt tag](http://www.djsmith.me/PLUGS/mcs/mcs.jpg)\r\n\r\n<h4>Jquery CSS Multi Column Select Box</h4>\r\n<p>A Simple plugin that will hide the Select control and then display a multicolumn dropdown (css)</p>\r\n<p>Uses the original form control so will work if JS is not enabled and the form can be processed as normal</p>\r\n\r\n\r\n<h2>Installation</h2>\r\n\r\n<pre>\r\n\r\nLoad the CSS:\r\n\"MultiColumnSelect/MultiColumnSelect.css\"\r\n\r\nInclude js plugin:\r\n\"MultiColumnSelect/MultiColumnSelect.js\"\r\n\r\n</pre>\r\n\r\n<h2>Set up your HTML</h2>\r\n\r\n```\r\n    <form action=\"test.php\" method=\"GET\">\r\n\r\n    <div class=\"selectcontrol\">\r\n        <select name=\"car\">\r\n                <option value=\"Audi\">Audi</option>\r\n                <option value=\"Bugatti\">Bugatti</option>\r\n                <option value=\"Chrysler\">Chrysler</option>\r\n                <option value=\"Daihatsu\">Daihatsu</option>\r\n                <option value=\"Ford\">Ford</option>\r\n                <option value=\"GM\">General Motors</option>\r\n                <option value=\"Honda\">Honda</option>\r\n                <option value=\"Infiniti\">Infiniti</option>\r\n                <option value=\"Jeep\">Jeep</option>\r\n                <option value=\"Kia\">Kia</option>\r\n     </select>\r\n    </div>\r\n    \r\n        <input type=\"submit\" value=\"Submit\" />\r\n    \r\n    </form>\r\n\r\n```\r\nWrap the select control with a div and give that container an ID or class\r\n\r\n<h2>CSS</h2>\r\n\r\n\r\n```\r\n.openmenubutton{\r\n}\r\n\r\n.menucontainer{\r\n        overflow:hidden;            \r\n        display:none;                    \r\n}\r\n\r\n.menuitem{\r\n}\r\n```\r\n\r\n\r\n<h2>Call the plugin</h2>\r\n\r\n```javascript\r\n$(\".selectcontrol\").MultiColumnSelect({\r\n\r\n            menuclass : 'multicolumnselect',     // class given to control\r\n            openmenu : 'openmenubutton',         // used to toggle menu open/closed\r\n            openmenutext : 'Choose',   // Text for toggle menu button\r\n            menucontainer : 'menucontainer',     // Container Class\r\n            menuitem : 'menuitem',               // Item Class\r\n            hideclass : 'hidden',                // hide Class\r\n            openclass : 'open',                  // Open Class\r\n            clearclass : 'clear',                // Clear Class\r\n            duration : 200                       // Animation Duration\r\n            \r\n            //TODO\r\n            \r\n            onOpenMenu: function(){};\r\n            onCloseMenu: function(){};\r\n            on...\r\n            \r\n            $.MulticolumnSelect.additem('ID','Value');\r\n            $.MulticolumnSelect.additem({{'ID','Value'},{'ID','Value'},{'ID','Value'}});\r\n            $.MulticolumnSelect.removeitem('ID');\r\n            $.MulticolumnSelect.destroy();\r\n            $.MulticolumnSelect.create({options});\r\n\r\n});\r\n```\r\n\r\n\r\n<h2>Tested on</h2>\r\n<ul>\r\n<li>IE7+</li>\r\n<li>Safari</li>\r\n<li>Firefox </li>\r\n<li>Chrome</li>\r\n</ul>\r\n\r\n\r\n<h2>License</h2>\r\n\r\n<p>The MIT License (MIT)</p>\r\n","google":"","note":"Don't delete this file! It's used internally to help with page regeneration."}